{"Items":[{"Sku":0,"BuyIcon":null,"Name":null,"Price":108990,"DiscountPrice":0,"ImageUrl":null,"Remains":0},{"Sku":0,"BuyIcon":null,"Name":null,"Price":108990,"DiscountPrice":0,"ImageUrl":null,"Remains":0},{"Sku":0,"BuyIcon":null,"Name":null,"Price":108990,"DiscountPrice":0,"ImageUrl":null,"Remains":0},{"Sku":0,"BuyIcon":null,"Name":null,"Price":108990,"DiscountPrice":0,"ImageUrl":null,"Remains":0},{"Sku":0,"BuyIcon":null,"Name":null,"Price":108990,"DiscountPrice":0,"ImageUrl":null,"Remains":0},{"Sku":0,"BuyIcon":null,"Name":null,"Price":108990,"DiscountPrice":0,"ImageUrl":null,"Remains":0},{"Sku":0,"BuyIcon":null,"Name":null,"Price":108990,"DiscountPrice":0,"ImageUrl":null,"Remains":0},{"Sku":0,"BuyIcon":null,"Name":null,"Price":108990,"DiscountPrice":0,"ImageUrl":null,"Remains":0},{"Sku":0,"BuyIcon":null,"Name":null,"Price":108990,"DiscountPrice":0,"ImageUrl":null,"Remains":0},{"Sku":0,"BuyIcon":null,"Name":null,"Price":108990,"DiscountPrice":0,"ImageUrl":null,"Remains":0},{"Sku":0,"BuyIcon":null,"Name":null,"Price":108990,"DiscountPrice":98990,"ImageUrl":null,"Remains":0},{"Sku":0,"BuyIcon":null,"Name":null,"Price":108990,"DiscountPrice":98990,"ImageUrl":null,"Remains":0},{"Sku":0,"BuyIcon":null,"Name":null,"Price":108990,"DiscountPrice":98990,"ImageUrl":null,"Remains":0},{"Sku":0,"BuyIcon":null,"Name":null,"Price":108990,"DiscountPrice":98990,"ImageUrl":null,"Remains":0},{"Sku":0,"BuyIcon":null,"Name":null,"Price":108990,"DiscountPrice":98990,"ImageUrl":null,"Remains":0},{"Sku":0,"BuyIcon":null,"Name":null,"Price":108990,"DiscountPrice":98990,"ImageUrl":null,"Remains":0},{"Sku":0,"BuyIcon":null,"Name":null,"Price":108990,"DiscountPrice":98990,"ImageUrl":null,"Remains":0},{"Sku":0,"BuyIcon":null,"Name":null,"Price":108990,"DiscountPrice":98990,"ImageUrl":null,"Remains":0},{"Sku":0,"BuyIcon":null,"Name":null,"Price":108990,"DiscountPrice":98990,"ImageUrl":null,"Remains":0},{"Sku":0,"BuyIcon":null,"Name":null,"Price":108990,"DiscountPrice":98990,"ImageUrl":null,"Remains":0},{"Sku":0,"BuyIcon":null,"Name":null,"Price":108990,"DiscountPrice":98990,"ImageUrl":null,"Remains":0},{"Sku":0,"BuyIcon":null,"Name":null,"Price":108990,"DiscountPrice":98990,"ImageUrl":null,"Remains":0},{"Sku":0,"BuyIcon":null,"Name":null,"Price":108990,"DiscountPrice":98990,"ImageUrl":null,"Remains":0},{"Sku":0,"BuyIcon":null,"Name":null,"Price":108990,"DiscountPrice":98990,"ImageUrl":null,"Remains":0},{"Sku":0,"BuyIcon":null,"Name":null,"Price":108990,"DiscountPrice":98990,"ImageUrl":null,"Remains":0},{"Sku":0,"BuyIcon":null,"Name":null,"Price":108990,"DiscountPrice":98990,"ImageUrl":null,"Remains":0},{"Sku":0,"BuyIcon":null,"Name":null,"Price":108990,"DiscountPrice":98990,"ImageUrl":null,"Remains":0},{"Sku":0,"BuyIcon":null,"Name":null,"Price":108990,"DiscountPrice":98990,"ImageUrl":null,"Remains":0},{"Sku":0,"BuyIcon":null,"Name":null,"Price":108990,"DiscountPrice":98990,"ImageUrl":null,"Remains":0},{"Sku":0,"BuyIcon":null,"Name":null,"Price":108990,"DiscountPrice":98990,"ImageUrl":null,"Remains":0},{"Sku":0,"BuyIcon":null,"Name":null,"Price":108990,"DiscountPrice":98990,"ImageUrl":null,"Remains":0},{"Sku":0,"BuyIcon":null,"Name":null,"Price":108990,"DiscountPrice":98990,"ImageUrl":null,"Remains":0},{"Sku":0,"BuyIcon":null,"Name":null,"Price":108990,"DiscountPrice":98990,"ImageUrl":null,"Remains":0},{"Sku":0,"BuyIcon":null,"Name":null,"Price":108990,"DiscountPrice":98990,"ImageUrl":null,"Remains":0},{"Sku":0,"BuyIcon":null,"Name":null,"Price":108990,"DiscountPrice":98990,"ImageUrl":null,"Remains":0},{"Sku":0,"BuyIcon":null,"Name":null,"Price":108990,"DiscountPrice":98990,"ImageUrl":null,"Remains":0},{"Sku":0,"BuyIcon":null,"Name":null,"Price":108990,"DiscountPrice":0,"ImageUrl":null,"Remains":0},{"Sku":0,"BuyIcon":null,"Name":null,"Price":108990,"DiscountPrice":0,"ImageUrl":null,"Remains":0},{"Sku":0,"BuyIcon":null,"Name":null,"Price":108990,"DiscountPrice":0,"ImageUrl":null,"Remains":0},{"Sku":0,"BuyIcon":null,"Name":null,"Price":108990,"DiscountPrice":0,"ImageUrl":null,"Remains":0},{"Sku":0,"BuyIcon":null,"Name":null,"Price":108990,"DiscountPrice":0,"ImageUrl":null,"Remains":0},{"Sku":0,"BuyIcon":null,"Name":null,"Price":108990,"DiscountPrice":0,"ImageUrl":null,"Remains":0},{"Sku":0,"BuyIcon":null,"Name":null,"Price":108990,"DiscountPrice":0,"ImageUrl":null,"Remains":0},{"Sku":0,"BuyIcon":null,"Name":null,"Price":108990,"DiscountPrice":0,"ImageUrl":null,"Remains":0},{"Sku":0,"BuyIcon":null,"Name":null,"Price":108990,"DiscountPrice":0,"ImageUrl":null,"Remains":0},{"Sku":0,"BuyIcon":null,"Name":null,"Price":108990,"DiscountPrice":0,"ImageUrl":null,"Remains":0},{"Sku":0,"BuyIcon":null,"Name":null,"Price":108990,"DiscountPrice":0,"ImageUrl":null,"Remains":0},{"Sku":0,"BuyIcon":null,"Name":null,"Price":108990,"DiscountPrice":0,"ImageUrl":null,"Remains":0},{"Sku":0,"BuyIcon":null,"Name":null,"Price":108990,"DiscountPrice":0,"ImageUrl":null,"Remains":0},{"Sku":0,"BuyIcon":null,"Name":null,"Price":108990,"DiscountPrice":0,"ImageUrl":null,"Remains":0},{"Sku":0,"BuyIcon":null,"Name":null,"Price":108990,"DiscountPrice":0,"ImageUrl":null,"Remains":0},{"Sku":0,"BuyIcon":null,"Name":null,"Price":108990,"DiscountPrice":0,"ImageUrl":null,"Remains":0},{"Sku":0,"BuyIcon":null,"Name":null,"Price":108990,"DiscountPrice":0,"ImageUrl":null,"Remains":0},{"Sku":0,"BuyIcon":null,"Name":null,"Price":108990,"DiscountPrice":0,"ImageUrl":null,"Remains":0},{"Sku":0,"BuyIcon":null,"Name":null,"Price":108990,"DiscountPrice":0,"ImageUrl":null,"Remains":0},{"Sku":0,"BuyIcon":null,"Name":null,"Price":108990,"DiscountPrice":0,"ImageUrl":null,"Remains":0},{"Sku":0,"BuyIcon":null,"Name":null,"Price":108990,"DiscountPrice":0,"ImageUrl":null,"Remains":0},{"Sku":0,"BuyIcon":null,"Name":null,"Price":108990,"DiscountPrice":0,"ImageUrl":null,"Remains":0},{"Sku":0,"BuyIcon":null,"Name":null,"Price":108990,"DiscountPrice":0,"ImageUrl":null,"Remains":0},{"Sku":0,"BuyIcon":null,"Name":null,"Price":108990,"DiscountPrice":0,"ImageUrl":null,"Remains":0},{"Sku":0,"BuyIcon":null,"Name":null,"Price":108990,"DiscountPrice":0,"ImageUrl":null,"Remains":0},{"Sku":0,"BuyIcon":null,"Name":null,"Price":108990,"DiscountPrice":0,"ImageUrl":null,"Remains":0},{"Sku":0,"BuyIcon":null,"Name":null,"Price":108990,"DiscountPrice":0,"ImageUrl":null,"Remains":0},{"Sku":0,"BuyIcon":null,"Name":null,"Price":108990,"DiscountPrice":0,"ImageUrl":null,"Remains":0},{"Sku":0,"BuyIcon":null,"Name":null,"Price":108990,"DiscountPrice":0,"ImageUrl":null,"Remains":0},{"Sku":0,"BuyIcon":null,"Name":null,"Price":108990,"DiscountPrice":0,"ImageUrl":null,"Remains":0},{"Sku":0,"BuyIcon":null,"Name":null,"Price":108990,"DiscountPrice":0,"ImageUrl":null,"Remains":0},{"Sku":0,"BuyIcon":null,"Name":null,"Price":108990,"DiscountPrice":0,"ImageUrl":null,"Remains":0},{"Sku":0,"BuyIcon":null,"Name":null,"Price":108990,"DiscountPrice":0,"ImageUrl":null,"Remains":0},{"Sku":0,"BuyIcon":null,"Name":null,"Price":108990,"DiscountPrice":0,"ImageUrl":null,"Remains":0},{"Sku":0,"BuyIcon":null,"Name":null,"Price":108990,"DiscountPrice":0,"ImageUrl":null,"Remains":0},{"Sku":0,"BuyIcon":null,"Name":null,"Price":108990,"DiscountPrice":0,"ImageUrl":null,"Remains":0},{"Sku":0,"BuyIcon":null,"Name":null,"Price":108990,"DiscountPrice":0,"ImageUrl":null,"Remains":0},{"Sku":0,"BuyIcon":null,"Name":null,"Price":108990,"DiscountPrice":0,"ImageUrl":null,"Remains":0},{"Sku":0,"BuyIcon":null,"Name":null,"Price":108990,"DiscountPrice":0,"ImageUrl":null,"Remains":0},{"Sku":0,"BuyIcon":null,"Name":null,"Price":108990,"DiscountPrice":0,"ImageUrl":null,"Remains":0},{"Sku":0,"BuyIcon":null,"Name":null,"Price":108990,"DiscountPrice":0,"ImageUrl":null,"Remains":0},{"Sku":0,"BuyIcon":null,"Name":null,"Price":108990,"DiscountPrice":0,"ImageUrl":null,"Remains":0},{"Sku":0,"BuyIcon":null,"Name":null,"Price":108990,"DiscountPrice":0,"ImageUrl":null,"Remains":0},{"Sku":0,"BuyIcon":null,"Name":null,"Price":108990,"DiscountPrice":0,"ImageUrl":null,"Remains":0},{"Sku":0,"BuyIcon":null,"Name":null,"Price":108990,"DiscountPrice":0,"ImageUrl":null,"Remains":0},{"Sku":0,"BuyIcon":null,"Name":null,"Price":108990,"DiscountPrice":0,"ImageUrl":null,"Remains":0},{"Sku":0,"BuyIcon":null,"Name":null,"Price":108990,"DiscountPrice":0,"ImageUrl":null,"Remains":0},{"Sku":0,"BuyIcon":null,"Name":null,"Price":108990,"DiscountPrice":0,"ImageUrl":null,"Remains":0},{"Sku":0,"BuyIcon":null,"Name":null,"Price":108990,"DiscountPrice":0,"ImageUrl":null,"Remains":0},{"Sku":0,"BuyIcon":null,"Name":null,"Price":108990,"DiscountPrice":0,"ImageUrl":null,"Remains":0},{"Sku":0,"BuyIcon":null,"Name":null,"Price":108990,"DiscountPrice":0,"ImageUrl":null,"Remains":0},{"Sku":0,"BuyIcon":null,"Name":null,"Price":108990,"DiscountPrice":0,"ImageUrl":null,"Remains":0},{"Sku":0,"BuyIcon":null,"Name":null,"Price":108990,"DiscountPrice":0,"ImageUrl":null,"Remains":0},{"Sku":0,"BuyIcon":null,"Name":null,"Price":108990,"DiscountPrice":0,"ImageUrl":null,"Remains":0},{"Sku":0,"BuyIcon":null,"Name":null,"Price":108990,"DiscountPrice":0,"ImageUrl":null,"Remains":0},{"Sku":0,"BuyIcon":null,"Name":null,"Price":108990,"DiscountPrice":0,"ImageUrl":null,"Remains":0},{"Sku":0,"BuyIcon":null,"Name":null,"Price":108990,"DiscountPrice":0,"ImageUrl":null,"Remains":0},{"Sku":0,"BuyIcon":null,"Name":null,"Price":108990,"DiscountPrice":0,"ImageUrl":null,"Remains":0},{"Sku":0,"BuyIcon":null,"Name":null,"Price":108990,"DiscountPrice":0,"ImageUrl":null,"Remains":0},{"Sku":0,"BuyIcon":null,"Name":null,"Price":108990,"DiscountPrice":0,"ImageUrl":null,"Remains":0},{"Sku":0,"BuyIcon":null,"Name":null,"Price":108990,"DiscountPrice":0,"ImageUrl":null,"Remains":0},{"Sku":0,"BuyIcon":null,"Name":null,"Price":108990,"DiscountPrice":0,"ImageUrl":null,"Remains":0},{"Sku":0,"BuyIcon":null,"Name":null,"Price":108990,"DiscountPrice":0,"ImageUrl":null,"Remains":0},{"Sku":0,"BuyIcon":null,"Name":null,"Price":108990,"DiscountPrice":0,"ImageUrl":null,"Remains":0},{"Sku":0,"BuyIcon":null,"Name":null,"Price":108990,"DiscountPrice":0,"ImageUrl":null,"Remains":0},{"Sku":0,"BuyIcon":null,"Name":null,"Price":108990,"DiscountPrice":0,"ImageUrl":null,"Remains":0},{"Sku":0,"BuyIcon":null,"Name":null,"Price":108990,"DiscountPrice":0,"ImageUrl":null,"Remains":0},{"Sku":0,"BuyIcon":null,"Name":null,"Price":108990,"DiscountPrice":0,"ImageUrl":null,"Remains":0},{"Sku":0,"BuyIcon":null,"Name":null,"Price":108990,"DiscountPrice":0,"ImageUrl":null,"Remains":0},{"Sku":0,"BuyIcon":null,"Name":null,"Price":108990,"DiscountPrice":0,"ImageUrl":null,"Remains":0},{"Sku":0,"BuyIcon":null,"Name":null,"Price":108990,"DiscountPrice":0,"ImageUrl":null,"Remains":0},{"Sku":0,"BuyIcon":null,"Name":null,"Price":108990,"DiscountPrice":0,"ImageUrl":null,"Remains":0},{"Sku":0,"BuyIcon":null,"Name":null,"Price":108990,"DiscountPrice":0,"ImageUrl":null,"Remains":0},{"Sku":0,"BuyIcon":null,"Name":null,"Price":108990,"DiscountPrice":0,"ImageUrl":null,"Remains":0},{"Sku":0,"BuyIcon":null,"Name":null,"Price":108990,"DiscountPrice":0,"ImageUrl":null,"Remains":0},{"Sku":0,"BuyIcon":null,"Name":null,"Price":108990,"DiscountPrice":0,"ImageUrl":null,"Remains":0},{"Sku":0,"BuyIcon":null,"Name":null,"Price":108990,"DiscountPrice":0,"ImageUrl":null,"Remains":0},{"Sku":0,"BuyIcon":null,"Name":null,"Price":108990,"DiscountPrice":0,"ImageUrl":null,"Remains":0},{"Sku":0,"BuyIcon":null,"Name":null,"Price":108990,"DiscountPrice":0,"ImageUrl":null,"Remains":0},{"Sku":0,"BuyIcon":null,"Name":null,"Price":108990,"DiscountPrice":0,"ImageUrl":null,"Remains":0},{"Sku":0,"BuyIcon":null,"Name":null,"Price":108990,"DiscountPrice":0,"ImageUrl":null,"Remains":0},{"Sku":0,"BuyIcon":null,"Name":null,"Price":108990,"DiscountPrice":0,"ImageUrl":null,"Remains":0},{"Sku":0,"BuyIcon":null,"Name":null,"Price":108990,"DiscountPrice":0,"ImageUrl":null,"Remains":0},{"Sku":0,"BuyIcon":null,"Name":null,"Price":108990,"DiscountPrice":0,"ImageUrl":null,"Remains":0},{"Sku":0,"BuyIcon":null,"Name":null,"Price":108990,"DiscountPrice":0,"ImageUrl":null,"Remains":0},{"Sku":0,"BuyIcon":null,"Name":null,"Price":108990,"DiscountPrice":0,"ImageUrl":null,"Remains":0},{"Sku":0,"BuyIcon":null,"Name":null,"Price":108990,"DiscountPrice":0,"ImageUrl":null,"Remains":0},{"Sku":0,"BuyIcon":null,"Name":null,"Price":108990,"DiscountPrice":0,"ImageUrl":null,"Remains":0},{"Sku":0,"BuyIcon":null,"Name":null,"Price":108990,"DiscountPrice":0,"ImageUrl":null,"Remains":0},{"Sku":0,"BuyIcon":null,"Name":null,"Price":108990,"DiscountPrice":0,"ImageUrl":null,"Remains":0},{"Sku":0,"BuyIcon":null,"Name":null,"Price":108990,"DiscountPrice":0,"ImageUrl":null,"Remains":0},{"Sku":0,"BuyIcon":null,"Name":null,"Price":108990,"DiscountPrice":0,"ImageUrl":null,"Remains":0},{"Sku":0,"BuyIcon":null,"Name":null,"Price":108990,"DiscountPrice":0,"ImageUrl":null,"Remains":0},{"Sku":0,"BuyIcon":null,"Name":null,"Price":108990,"DiscountPrice":0,"ImageUrl":null,"Remains":0},{"Sku":0,"BuyIcon":null,"Name":null,"Price":108990,"DiscountPrice":0,"ImageUrl":null,"Remains":0},{"Sku":0,"BuyIcon":null,"Name":null,"Price":108990,"DiscountPrice":0,"ImageUrl":null,"Remains":0},{"Sku":0,"BuyIcon":null,"Name":null,"Price":108990,"DiscountPrice":0,"ImageUrl":null,"Remains":0},{"Sku":0,"BuyIcon":null,"Name":null,"Price":108990,"DiscountPrice":0,"ImageUrl":null,"Remains":0},{"Sku":0,"BuyIcon":null,"Name":null,"Price":108990,"DiscountPrice":0,"ImageUrl":null,"Remains":0},{"Sku":0,"BuyIcon":null,"Name":null,"Price":108990,"DiscountPrice":0,"ImageUrl":null,"Remains":0},{"Sku":0,"BuyIcon":null,"Name":null,"Price":108990,"DiscountPrice":0,"ImageUrl":null,"Remains":0},{"Sku":0,"BuyIcon":null,"Name":null,"Price":108990,"DiscountPrice":0,"ImageUrl":null,"Remains":0},{"Sku":0,"BuyIcon":null,"Name":null,"Price":108990,"DiscountPrice":0,"ImageUrl":null,"Remains":0},{"Sku":0,"BuyIcon":null,"Name":null,"Price":108990,"DiscountPrice":0,"ImageUrl":null,"Remains":0},{"Sku":0,"BuyIcon":null,"Name":null,"Price":108990,"DiscountPrice":0,"ImageUrl":null,"Remains":0},{"Sku":0,"BuyIcon":null,"Name":null,"Price":108990,"DiscountPrice":0,"ImageUrl":null,"Remains":0},{"Sku":0,"BuyIcon":null,"Name":null,"Price":108990,"DiscountPrice":0,"ImageUrl":null,"Remains":0},{"Sku":0,"BuyIcon":null,"Name":null,"Price":108990,"DiscountPrice":0,"ImageUrl":null,"Remains":0},{"Sku":0,"BuyIcon":null,"Name":null,"Price":108990,"DiscountPrice":0,"ImageUrl":null,"Remains":0},{"Sku":0,"BuyIcon":null,"Name":null,"Price":108990,"DiscountPrice":0,"ImageUrl":null,"Remains":0},{"Sku":0,"BuyIcon":null,"Name":null,"Price":108990,"DiscountPrice":0,"ImageUrl":null,"Remains":0},{"Sku":0,"BuyIcon":null,"Name":null,"Price":108990,"DiscountPrice":0,"ImageUrl":null,"Remains":0},{"Sku":0,"BuyIcon":null,"Name":null,"Price":108990,"DiscountPrice":0,"ImageUrl":null,"Remains":0},{"Sku":0,"BuyIcon":null,"Name":null,"Price":108990,"DiscountPrice":0,"ImageUrl":null,"Remains":0},{"Sku":0,"BuyIcon":null,"Name":null,"Price":108990,"DiscountPrice":0,"ImageUrl":null,"Remains":0},{"Sku":0,"BuyIcon":null,"Name":null,"Price":108990,"DiscountPrice":0,"ImageUrl":null,"Remains":0},{"Sku":0,"BuyIcon":null,"Name":null,"Price":108990,"DiscountPrice":0,"ImageUrl":null,"Remains":0},{"Sku":0,"BuyIcon":null,"Name":null,"Price":108990,"DiscountPrice":0,"ImageUrl":null,"Remains":0},{"Sku":0,"BuyIcon":null,"Name":null,"Price":108990,"DiscountPrice":0,"ImageUrl":null,"Remains":0},{"Sku":0,"BuyIcon":null,"Name":null,"Price":108990,"DiscountPrice":0,"ImageUrl":null,"Remains":0},{"Sku":0,"BuyIcon":null,"Name":null,"Price":108990,"DiscountPrice":0,"ImageUrl":null,"Remains":0},{"Sku":0,"BuyIcon":null,"Name":null,"Price":108990,"DiscountPrice":0,"ImageUrl":null,"Remains":0},{"Sku":0,"BuyIcon":null,"Name":null,"Price":108990,"DiscountPrice":0,"ImageUrl":null,"Remains":0},{"Sku":0,"BuyIcon":null,"Name":null,"Price":108990,"DiscountPrice":0,"ImageUrl":null,"Remains":0},{"Sku":0,"BuyIcon":null,"Name":null,"Price":108990,"DiscountPrice":0,"ImageUrl":null,"Remains":0},{"Sku":0,"BuyIcon":null,"Name":null,"Price":108990,"DiscountPrice":0,"ImageUrl":null,"Remains":0},{"Sku":0,"BuyIcon":null,"Name":null,"Price":108990,"DiscountPrice":0,"ImageUrl":null,"Remains":0},{"Sku":0,"BuyIcon":null,"Name":null,"Price":108990,"DiscountPrice":0,"ImageUrl":null,"Remains":0},{"Sku":0,"BuyIcon":null,"Name":null,"Price":108990,"DiscountPrice":0,"ImageUrl":null,"Remains":0},{"Sku":0,"BuyIcon":null,"Name":null,"Price":108990,"DiscountPrice":0,"ImageUrl":null,"Remains":0},{"Sku":0,"BuyIcon":null,"Name":null,"Price":108990,"DiscountPrice":0,"ImageUrl":null,"Remains":0},{"Sku":0,"BuyIcon":null,"Name":null,"Price":108990,"DiscountPrice":0,"ImageUrl":null,"Remains":0},{"Sku":0,"BuyIcon":null,"Name":null,"Price":108990,"DiscountPrice":0,"ImageUrl":null,"Remains":0},{"Sku":0,"BuyIcon":null,"Name":null,"Price":108990,"DiscountPrice":0,"ImageUrl":null,"Remains":0},{"Sku":0,"BuyIcon":null,"Name":null,"Price":108990,"DiscountPrice":0,"ImageUrl":null,"Remains":0},{"Sku":0,"BuyIcon":null,"Name":null,"Price":108990,"DiscountPrice":0,"ImageUrl":null,"Remains":0},{"Sku":0,"BuyIcon":null,"Name":null,"Price":108990,"DiscountPrice":0,"ImageUrl":null,"Remains":0},{"Sku":0,"BuyIcon":null,"Name":null,"Price":108990,"DiscountPrice":0,"ImageUrl":null,"Remains":0},{"Sku":0,"BuyIcon":null,"Name":null,"Price":108990,"DiscountPrice":0,"ImageUrl":null,"Remains":0}],"Count":0}